oneroster/__init__.py
oneroster/classlink.py
oneroster/clever.py
oneroster/util.py
tests/__init__.py
tests/conftest.py
tests/test_clever.py
tests/test_integration.py
tests/test_util.py
tests/util.py
oneroster-0.0.17.dist-info/LICENSE.txt
oneroster-0.0.17.dist-info/METADATA
oneroster-0.0.17.dist-info/WHEEL
oneroster-0.0.17.dist-info/top_level.txt
oneroster-0.0.17.dist-info/RECORD
