Metadata-Version: 2.1
Name: oneroster
Version: 0.0.17
Summary: Simple Oneroster client for user management
Home-page: https://github.com/vossenv/oneroster-python
Maintainer: Danimae Vossen
Maintainer-email: vossen.dm@gmail.com
License: MIT
Platform: UNKNOWN
Classifier: Programming Language :: Python :: 2.7
Classifier: Programming Language :: Python :: 3.4
Classifier: Programming Language :: Python :: 3.5
Classifier: Programming Language :: Python :: 3.6
Classifier: License :: OSI Approved :: MIT License
Classifier: Intended Audience :: Developers
Classifier: Intended Audience :: System Administrators
Requires-Dist: six
Requires-Dist: requests
